catasta/__init__.py
catasta/archway/__init__.py
catasta/archway/archway.py
catasta/dataclasses/__init__.py
catasta/dataclasses/eval_info.py
catasta/dataclasses/optimization_info.py
catasta/dataclasses/prediction_info.py
catasta/dataclasses/train_info.py
catasta/dataclasses/trial_info.py
catasta/dataset/__init__.py
catasta/dataset/catasta_dataset.py
catasta/foundation/__init__.py
catasta/foundation/foundation.py
catasta/foundation/utils/__init__.py
catasta/foundation/utils/optimization_logger.py
catasta/foundation/utils/sampler_factory.py
catasta/log/ansi.py
catasta/models/__init__.py
catasta/models/cnn_image_classifier.py
catasta/models/feedforward_image_classifier.py
catasta/models/feedforward_regressor.py
catasta/models/gp_head_regressor.py
catasta/models/gp_regressor.py
catasta/models/mamba_fft_image_classifier.py
catasta/models/mamba_fft_regressor.py
catasta/models/mamba_image_classifier.py
catasta/models/mamba_regressor.py
catasta/models/multi_headed_feedforward_regressor.py
catasta/models/multi_headed_transformer_regressor.py
catasta/models/transformer_fft_image_classifier.py
catasta/models/transformer_fft_regressor.py
catasta/models/transformer_image_classifier.py
catasta/models/transformer_regressor.py
catasta/scaffold/__init__.py
catasta/scaffold/scaffold.py
catasta/scaffold/utils/__init__.py
catasta/scaffold/utils/loss_function_factory.py
catasta/scaffold/utils/model_state_manager.py
catasta/scaffold/utils/objective_function_factory.py
catasta/scaffold/utils/optimizer_factory.py
catasta/scaffold/utils/training_logger.py
catasta/transformations/__init__.py
catasta/transformations/custom.py
catasta/transformations/decimation.py
catasta/transformations/diff_and_concat.py
catasta/transformations/fir_filtering.py
catasta/transformations/identity.py
catasta/transformations/kalman_filter.py
catasta/transformations/normalization.py
catasta/transformations/slicing.py
catasta/transformations/transformation.py
catasta/transformations/window_sliding.py
catasta-0.4.3.dist-info/METADATA
catasta-0.4.3.dist-info/WHEEL
catasta-0.4.3.dist-info/licenses/LICENSE
catasta-0.4.3.dist-info/RECORD
