Metadata-Version: 2.4
Name: catasta
Version: 0.4.3
Summary: _Catasta_ is a Python library designed to simplify the process of Machine Learning model experimentation. Optimization, training, evaluation and inference all in one place!
Project-URL: Homepage, https://github.com/vistormu/catasta
Project-URL: Issues, https://github.com/vistormu/catasta/issues
Author: Vistor
License-File: LICENSE
Classifier: License :: OSI Approved :: MIT License
Classifier: Operating System :: OS Independent
Classifier: Programming Language :: Python :: 3
Requires-Python: >=3.10
Requires-Dist: einops
Requires-Dist: gpytorch
Requires-Dist: numpy
Requires-Dist: optuna
Requires-Dist: pandas
Requires-Dist: pillow
Requires-Dist: scipy
Requires-Dist: torch
